.coveragerc
.mailmap
.testr.conf
AUTHORS
ChangeLog
LICENSE
README.md
README.rst
babel.cfg
requirements.txt
setup.cfg
setup.py
test-requirements.txt
tox.ini
catena/__init__.py
catena.egg-info/PKG-INFO
catena.egg-info/SOURCES.txt
catena.egg-info/dependency_links.txt
catena.egg-info/entry_points.txt
catena.egg-info/not-zip-safe
catena.egg-info/pbr.json
catena.egg-info/requires.txt
catena.egg-info/top_level.txt
catena/api/__init__.py
catena/api/app.py
catena/api/common/__init__.py
catena/api/common/middleware.py
catena/api/common/utils.py
catena/api/v1/__init__.py
catena/api/v1/backends.py
catena/api/v1/chains.py
catena/api/v1/cloud.py
catena/api/v1/homedoc.py
catena/api/v1/nodes.py
catena/chain_backends/__init__.py
catena/chain_backends/ethereum/__init__.py
catena/chain_backends/ethereum/ethereum_api.py
catena/chain_backends/ethereum/ansible/deploy-controller.yml
catena/chain_backends/ethereum/ansible/deploy-geth.yml
catena/chain_backends/ethereum/ansible/eth-netstats.service
catena/chain_backends/ethereum/ansible/geth.service
catena/clouds/__init__.py
catena/clouds/azure_api.py
catena/clouds/openstack_api.py
catena/cmd/__init__.py
catena/cmd/manage.py
catena/cmd/server.py
catena/common/__init__.py
catena/common/ansible_utils.py
catena/common/config.py
catena/common/utils.py
catena/db/__init__.py
catena/db/sqlalchemy/__init__.py
catena/db/sqlalchemy/api.py
catena/db/sqlalchemy/models.py
catena/service/__init__.py
catena/service/service.py
catena/tests/__init__.py
catena/tests/base.py
catena/tests/test_catena.py
config-generator/catena.conf
doc/Deployment of an Ethereum Blockchain with docker.xml
doc/Deployment of an Ethereum Blockchain.png
doc/Deployment of an Ethereum Blockchain.xml
doc/README.md
doc/Sourcecode Components.png
doc/Sourcecode Components.xml
doc/source/conf.py
doc/source/contributing.rst
doc/source/index.rst
doc/source/installation.rst
doc/source/readme.rst
doc/source/usage.rst
etc/api.conf.sample
golang/enode-fetcher.go
golang/node-registrator.go
releasenotes/notes/.placeholder
releasenotes/source/conf.py
releasenotes/source/index.rst
releasenotes/source/unreleased.rst
releasenotes/source/_static/.placeholder
releasenotes/source/_templates/.placeholder