Metadata-Version: 1.1
Name: catena
Version: 0.0.1.dev8
Summary: Catena is blockchain as a service.
Home-page: https://github.com/HewlettPackard/catena
Author: Hewlett Packard Enterprise
Author-email: blockchain@lists.osp.hpe.com
License: UNKNOWN
Platform: UNKNOWN
Classifier: Intended Audience :: Information Technology
Classifier: Intended Audience :: System Administrators
Classifier: License :: OSI Approved :: Apache Software License
Classifier: Operating System :: POSIX :: Linux
Classifier: Programming Language :: Python
Classifier: Programming Language :: Python :: 2
Classifier: Programming Language :: Python :: 2.7
Classifier: Programming Language :: Python :: 3
Classifier: Programming Language :: Python :: 3.3
Classifier: Programming Language :: Python :: 3.4
